blockdoc/__init__.py
blockdoc/api/__init__.py
blockdoc/conversions/__init__.py
blockdoc/conversions/markdown.py
blockdoc/core/__init__.py
blockdoc/core/block.py
blockdoc/core/document.py
blockdoc/renderers/__init__.py
blockdoc/renderers/html.py
blockdoc/renderers/markdown.py
blockdoc/schema/__init__.py
blockdoc/schema/blockdoc.schema.json
blockdoc/schema/loader.py
blockdoc/utils/__init__.py
blockdoc/utils/sanitize.py
blockdoc-1.1.0.dist-info/licenses/LICENSE
tests/__init__.py
tests/conversions/__init__.py
tests/conversions/test_markdown.py
tests/core/__init__.py
tests/core/test_block.py
tests/core/test_document.py
blockdoc-1.1.0.dist-info/METADATA
blockdoc-1.1.0.dist-info/WHEEL
blockdoc-1.1.0.dist-info/top_level.txt
blockdoc-1.1.0.dist-info/RECORD
